ChangeLog
DEPENDS
MANIFEST.in
README
setup.py
tox.ini
bin/pybill
bin/pybill.bat
doc/makefile
doc/_themes/lglb_doc/layout.html
doc/_themes/lglb_doc/logilab_logo.pdf
doc/_themes/lglb_doc/theme.conf
doc/_themes/lglb_doc/static/contents.png
doc/_themes/lglb_doc/static/lglb-sphinx-doc.css
doc/_themes/lglb_doc/static/logilab_logo.png
doc/_themes/lglb_doc/static/navigation.png
doc/dev-manual/README
doc/dev-manual/commandline_index.rst
doc/dev-manual/conf.py
doc/dev-manual/index.rst
doc/dev-manual/lib_accounting_index.rst
doc/dev-manual/lib_config_index.rst
doc/dev-manual/lib_controller_index.rst
doc/dev-manual/lib_entities_index.rst
doc/dev-manual/lib_errors_index.rst
doc/dev-manual/lib_index.rst
doc/dev-manual/lib_pdfwriters_index.rst
doc/dev-manual/lib_xmlreaders_index.rst
doc/dev-manual/lib_xmlwriters_index.rst
doc/dev-manual/makefile
doc/dev-manual/pybill_index.rst
doc/install-manual/README
doc/install-manual/conf.py
doc/install-manual/dependencies.rst
doc/install-manual/index.rst
doc/install-manual/installable-packages.rst
doc/install-manual/makefile
doc/install-manual/manual-installation.rst
doc/user-manual/README
doc/user-manual/acc-doc-description.rst
doc/user-manual/acc-entries-generation.rst
doc/user-manual/command-line-run.rst
doc/user-manual/conf.py
doc/user-manual/config-specification.rst
doc/user-manual/index.rst
doc/user-manual/makefile
pybill/__init__.py
pybill/__main__.py
pybill/__pkginfo__.py
pybill/main.py
pybill.egg-info/PKG-INFO
pybill.egg-info/SOURCES.txt
pybill.egg-info/dependency_links.txt
pybill.egg-info/requires.txt
pybill.egg-info/top_level.txt
pybill/commandline/__init__.py
pybill/commandline/ui.py
pybill/configs/README
pybill/configs/default.xml
pybill/examples/genexamples.py
pybill/examples/configs/config-en.xml
pybill/examples/configs/config-fr.xml
pybill/examples/inputs/01_bill-simple.xml
pybill/examples/inputs/02_bill-with-details.xml
pybill/examples/inputs/03_bill-with-remarks.xml
pybill/examples/inputs/04_bill-with-various-vat-rates.xml
pybill/examples/inputs/05_bill-with-no-vat.xml
pybill/examples/inputs/06_bill_with-vat-and-no-vat.xml
