Metadata-Version: 1.1
Name: pybill
Version: 1.2.0
Summary: PDF formatting tool for bills
Home-page: http://www.logilab.org/project/pybill
Author: Olivier Cayrol
Author-email: olivier.cayrol@logilab.fr
License: LGPL
Platform: UNKNOWN
Classifier: Topic :: Utilities
Classifier: Programming Language :: Python
Classifier: Programming Language :: Python :: 3 :: Only
